{
    "name": "App\\Http\\Controllers\\General\\GeneralMapController",
    "line": 17,
    "short_desc": "",
    "long_desc": "",
    "hint": null,
    "tags": [],
    "namespace": "App\\Http\\Controllers\\General",
    "file": "app\/\\Http\\Controllers\\General\\GeneralMapController.php",
    "relative_file": null,
    "hash": "c0a6dbe39b6907d20565654ec332d9df4fb5a8d2",
    "parent": "App\\Http\\Controllers\\Controller",
    "modifiers": 0,
    "is_trait": false,
    "is_interface": false,
    "aliases": {
        "Request": "Illuminate\\Http\\Request",
        "Controller": "App\\Http\\Controllers\\Controller",
        "CvGeoJson": "App\\CvGeoJson",
        "CvTask": "App\\CvTask",
        "GeneralSubTypeTaskController": "App\\Http\\Controllers\\General\\GeneralSubTypeTaskController",
        "CvBudgetActionMaterial": "App\\CvBudgetActionMaterial",
        "CvBudget": "App\\CvBudget",
        "CvProcess": "App\\CvProcess",
        "CvProperty": "App\\CvProperty",
        "SearchAlgoliaController": "App\\Http\\Controllers\\Search\\SearchAlgoliaController",
        "GeneralSearchController": "App\\Http\\Controllers\\General\\GeneralSearchController"
    },
    "errors": [],
    "interfaces": [],
    "traits": [],
    "properties": [],
    "methods": {
        "propertyGeoJsonTask": {
            "name": "propertyGeoJsonTask",
            "line": 21,
            "short_desc": "",
            "long_desc": "",
            "hint": null,
            "hint_desc": null,
            "tags": [],
            "modifiers": 1,
            "is_by_ref": "",
            "exceptions": [],
            "errors": [],
            "parameters": {
                "request": {
                    "name": "request",
                    "line": 21,
                    "short_desc": null,
                    "long_desc": null,
                    "hint": [
                        [
                            "\\Illuminate\\Http\\Request",
                            false
                        ]
                    ],
                    "tags": [],
                    "modifiers": {
                        "nodeType": "Name_FullyQualified",
                        "parts": [
                            "Illuminate",
                            "Http",
                            "Request"
                        ],
                        "attributes": {
                            "startLine": 21,
                            "endLine": 21
                        }
                    },
                    "default": null,
                    "variadic": false,
                    "is_by_ref": false
                }
            }
        },
        "updateMapGeoJson": {
            "name": "updateMapGeoJson",
            "line": 151,
            "short_desc": "",
            "long_desc": "",
            "hint": null,
            "hint_desc": null,
            "tags": [],
            "modifiers": 1,
            "is_by_ref": "",
            "exceptions": [],
            "errors": [],
            "parameters": {
                "request": {
                    "name": "request",
                    "line": 151,
                    "short_desc": null,
                    "long_desc": null,
                    "hint": [
                        [
                            "\\Illuminate\\Http\\Request",
                            false
                        ]
                    ],
                    "tags": [],
                    "modifiers": {
                        "nodeType": "Name_FullyQualified",
                        "parts": [
                            "Illuminate",
                            "Http",
                            "Request"
                        ],
                        "attributes": {
                            "startLine": 151,
                            "endLine": 151
                        }
                    },
                    "default": null,
                    "variadic": false,
                    "is_by_ref": false
                }
            }
        },
        "consultMapTask": {
            "name": "consultMapTask",
            "line": 246,
            "short_desc": "",
            "long_desc": "",
            "hint": null,
            "hint_desc": null,
            "tags": [],
            "modifiers": 1,
            "is_by_ref": "",
            "exceptions": [],
            "errors": [],
            "parameters": {
                "id": {
                    "name": "id",
                    "line": 246,
                    "short_desc": null,
                    "long_desc": null,
                    "hint": null,
                    "tags": [],
                    "modifiers": null,
                    "default": null,
                    "variadic": false,
                    "is_by_ref": false
                }
            }
        },
        "approvedMap": {
            "name": "approvedMap",
            "line": 259,
            "short_desc": "",
            "long_desc": "",
            "hint": null,
            "hint_desc": null,
            "tags": [],
            "modifiers": 1,
            "is_by_ref": "",
            "exceptions": [],
            "errors": [],
            "parameters": {
                "id": {
                    "name": "id",
                    "line": 259,
                    "short_desc": null,
                    "long_desc": null,
                    "hint": null,
                    "tags": [],
                    "modifiers": null,
                    "default": null,
                    "variadic": false,
                    "is_by_ref": false
                }
            }
        },
        "consultProcessGeojsonWithBudget": {
            "name": "consultProcessGeojsonWithBudget",
            "line": 265,
            "short_desc": "",
            "long_desc": "",
            "hint": null,
            "hint_desc": null,
            "tags": [],
            "modifiers": 1,
            "is_by_ref": "",
            "exceptions": [],
            "errors": [],
            "parameters": {
                "id": {
                    "name": "id",
                    "line": 265,
                    "short_desc": null,
                    "long_desc": null,
                    "hint": null,
                    "tags": [],
                    "modifiers": null,
                    "default": null,
                    "variadic": false,
                    "is_by_ref": false
                }
            }
        },
        "consultHashMaterialsActions": {
            "name": "consultHashMaterialsActions",
            "line": 327,
            "short_desc": "",
            "long_desc": "",
            "hint": null,
            "hint_desc": null,
            "tags": [],
            "modifiers": 1,
            "is_by_ref": "",
            "exceptions": [],
            "errors": [],
            "parameters": {
                "hash": {
                    "name": "hash",
                    "line": 327,
                    "short_desc": null,
                    "long_desc": null,
                    "hint": null,
                    "tags": [],
                    "modifiers": null,
                    "default": null,
                    "variadic": false,
                    "is_by_ref": false
                }
            }
        },
        "infoSearchGeoJson": {
            "name": "infoSearchGeoJson",
            "line": 362,
            "short_desc": "",
            "long_desc": "",
            "hint": null,
            "hint_desc": null,
            "tags": [],
            "modifiers": 1,
            "is_by_ref": "",
            "exceptions": [],
            "errors": [],
            "parameters": {
                "map_geo_json_id": {
                    "name": "map_geo_json_id",
                    "line": 362,
                    "short_desc": null,
                    "long_desc": null,
                    "hint": null,
                    "tags": [],
                    "modifiers": null,
                    "default": null,
                    "variadic": false,
                    "is_by_ref": false
                }
            }
        }
    },
    "constants": []
}