{
    "name": "App\\CvPqrs",
    "line": 8,
    "short_desc": "",
    "long_desc": "",
    "hint": null,
    "tags": [],
    "namespace": "App",
    "file": "app\/\\CvPqrs.php",
    "relative_file": null,
    "hash": "9f366fa37fe2aa1e03b1e61e2ece2ffef2c22373",
    "parent": "Illuminate\\Database\\Eloquent\\Model",
    "modifiers": 0,
    "is_trait": false,
    "is_interface": false,
    "aliases": {
        "Model": "Illuminate\\Database\\Eloquent\\Model",
        "CvResponsePqrs": "App\\CvResponsePqrs"
    },
    "errors": [],
    "interfaces": [],
    "traits": [],
    "properties": {
        "table": {
            "name": "table",
            "line": 10,
            "short_desc": "",
            "long_desc": "",
            "hint": null,
            "hint_desc": null,
            "tags": [],
            "modifiers": 2,
            "default": {
                "nodeType": "Scalar_String",
                "value": "cv_pqrs",
                "attributes": {
                    "startLine": 10,
                    "endLine": 10,
                    "kind": 2
                }
            },
            "errors": []
        }
    },
    "methods": {
        "responsePqrs": {
            "name": "responsePqrs",
            "line": 14,
            "short_desc": "",
            "long_desc": "",
            "hint": null,
            "hint_desc": null,
            "tags": [],
            "modifiers": 1,
            "is_by_ref": "",
            "exceptions": [],
            "errors": [],
            "parameters": []
        }
    },
    "constants": []
}